py4hy/__init__.py
py4hy/courses.py
py4hy/people.py
py4hy-0.0.1.dist-info/LICENCE
py4hy-0.0.1.dist-info/METADATA
py4hy-0.0.1.dist-info/WHEEL
py4hy-0.0.1.dist-info/top_level.txt
py4hy-0.0.1.dist-info/RECORD
