Metadata-Version: 2.1
Name: py4hy
Version: 0.0.1
Summary: Python libraries for University of Helsinki internal services
Home-page: https://github.com/uh-soco/pyhy/
Author: Matti Nelimarkka
Author-email: matti.nelimarkka@helsinki.fi
License: UNKNOWN
Project-URL: Bug Tracker, https://github.com/uh-soco/pyhy/issues
Platform: UNKNOWN
Classifier: Programming Language :: Python :: 3
Classifier: License :: OSI Approved :: MIT License
Classifier: Operating System :: OS Independent
Requires-Python: >=3.5
License-File: LICENCE
Requires-Dist: requests
